token_count/__init__.py
token_count/main.py
token_count/token_count.py
token_count-0.2.1.dist-info/LICENSE
token_count-0.2.1.dist-info/METADATA
token_count-0.2.1.dist-info/WHEEL
token_count-0.2.1.dist-info/entry_points.txt
token_count-0.2.1.dist-info/top_level.txt
token_count-0.2.1.dist-info/RECORD
