Metadata-Version: 2.1
Name: token-count
Version: 0.2.1
Summary: Count the number of tokens in a text string or file, similar to the Unix 'wc' utility.
Home-page: https://github.com/felvin-search/token-count
Author: Felvin
Author-email: team@felvin.com
Classifier: Development Status :: 3 - Alpha
Classifier: License :: OSI Approved :: MIT License
Classifier: Programming Language :: Python :: 3
Classifier: Programming Language :: Python :: 3.6
Classifier: Programming Language :: Python :: 3.7
Classifier: Programming Language :: Python :: 3.8
Classifier: Programming Language :: Python :: 3.9
License-File: LICENSE
